amberelectric/__init__.py
amberelectric/configuration.py
amberelectric/exceptions.py
amberelectric/model_utils.py
amberelectric/rest.py
amberelectric/api/__init__.py
amberelectric/api/amber_api.py
amberelectric/model/__init__.py
amberelectric/model/actual_interval.py
amberelectric/model/channel.py
amberelectric/model/current_interval.py
amberelectric/model/forecast_interval.py
amberelectric/model/interval.py
amberelectric/model/range.py
amberelectric/model/site.py
amberelectric/model/tariff_information.py
amberelectric/model/usage.py
amberelectric.py-1.0.0.dist-info/METADATA
amberelectric.py-1.0.0.dist-info/WHEEL
amberelectric.py-1.0.0.dist-info/top_level.txt
amberelectric.py-1.0.0.dist-info/RECORD
