Metadata-Version: 2.1
Name: amberelectric.py
Version: 1.0.0
Summary: Interface to the Amber Electric API, allowing you to download current and forecast price, as well as download your historic usage.
Home-page: https://github.com/madpilot/amberelectric.py
Author: Myles Eftos
Author-email: myles@madpilot.com.au
License: UNKNOWN
Keywords: amberelectric
Platform: UNKNOWN
Requires-Python: >=3.6
Requires-Dist: urllib3 (>=1.25.3)
Requires-Dist: python-dateutil
